flaskactions
