Metadata-Version: 1.0
Name: flask-google-actions
Version: 1.0.2
Summary: Client library for Actions on Google using python and flask
Home-page: https://github.com/caycewilliams/flask-actions-on-google-python
Author: Cayce Williams
Author-email: caycewilliams77@gmail.com
License: MIT
Platform: UNKNOWN
